feed_manager/__init__.py
feed_manager/consumer.py
feed_manager/generator.py
feed_manager/storage.py
feed_manager/translator.py
misp_feed_manager-0.3.2.data/scripts/consume_feed.py
misp_feed_manager-0.3.2.data/scripts/generate_feed.py
misp_feed_manager-0.3.2.dist-info/LICENSE
misp_feed_manager-0.3.2.dist-info/METADATA
misp_feed_manager-0.3.2.dist-info/NOTICE
misp_feed_manager-0.3.2.dist-info/WHEEL
misp_feed_manager-0.3.2.dist-info/top_level.txt
misp_feed_manager-0.3.2.dist-info/RECORD
