Metadata-Version: 2.1
Name: misp-feed-manager
Version: 0.3.2
Summary: Set of utilities to manage MISP feeds
Home-page: https://github.com/vmware-labs/feed-manager-for-misp/
Author: Stefano Ortolani
Project-URL: Bug Tracker, https://github.com/vmware-labs/feed-manager-for-misp/issues
Classifier: Development Status :: 3 - Alpha
Classifier: Intended Audience :: Developers
Classifier: License :: OSI Approved :: BSD License
Classifier: Programming Language :: Python :: 3
Classifier: Operating System :: OS Independent
Classifier: Topic :: Security
Classifier: Topic :: Software Development :: Libraries :: Python Modules
Requires-Python: >=3.9
License-File: LICENSE
License-File: NOTICE
Requires-Dist: google-cloud-storage
Requires-Dist: requests
Provides-Extra: misp
Requires-Dist: pymisp ; extra == 'misp'
